color_manager/__init__.py
color_manager/gui.py
color_manager/ngtk.py
color_manager/utils.py
color_manager_nv-1.0.0.dist-info/LICENSE
color_manager_nv-1.0.0.dist-info/METADATA
color_manager_nv-1.0.0.dist-info/WHEEL
color_manager_nv-1.0.0.dist-info/top_level.txt
color_manager_nv-1.0.0.dist-info/RECORD
